connect/__init__.py
connect/autogen.py
connect/api/__init__.py
connect/flow/__init__.py
connect/logger/__init__.py
connect/models/__init__.py
connect/util/__init__.py
connect_sdk_haxe_port-22.2.0.dist-info/LICENSE
connect_sdk_haxe_port-22.2.0.dist-info/METADATA
connect_sdk_haxe_port-22.2.0.dist-info/WHEEL
connect_sdk_haxe_port-22.2.0.dist-info/top_level.txt
connect_sdk_haxe_port-22.2.0.dist-info/RECORD
