Metadata-Version: 2.1
Name: connect-sdk-haxe-port
Version: 22.2.0
Summary: CloudBlue Connect SDK, generated from Haxe
Home-page: https://github.com/cloudblue/connect-haxe-sdk
Author: Ingram Micro
Author-email: connect-service-account@ingrammicro.com
License: Apache Software License
Keywords: connect sdk cloudblue ingram micro ingrammicro cloud automation
Platform: UNKNOWN
Requires-Dist: requests (==2.21.0)
